[{"CardNumber":"5168757354936355","ApplicationCode":"286088","TimeStamp":"2020-02-05T14:52:00+02:00","Amount":{"Amount":1638.00,"Currency":0},"IsIncome":true,"IsExpence":false,"Rest":{"Amount":20514.69,"Currency":0},"Terminal":"PRIVAT WAGE - UAH, CP9800ZP","Description":"Социальная помощь, Центральне управлiнн"},{"CardNumber":"5168757354936355","ApplicationCode":"124089","TimeStamp":"2020-02-07T13:48:00+02:00","Amount":{"Amount":200.00,"Currency":0},"IsIncome":true,"IsExpence":false,"Rest":{"Amount":20714.69,"Currency":0},"Terminal":"PrivatBank, CP980H48","Description":"Перевод с карты ПриватБанка через приложение Приват24. Отправитель: Бура Людмила Олексіївна"}]